[
    {
        "id": "1",
        "text": "Укажите номера предложений, в которых верно передана ГЛАВНАЯ информация, содержащаяся в тексте. Запишите номера этих предложений. 1)Оказывается, всем богатством того, что называется вкусом, человек обязан своему обонянию. (2)<...> объясняется тот факт, что при сильной простуде, когда обоняние на время пропадает, пища становится безвкусной. (3)При простуде мы получаем информацию о вкусе только с помощью рецепторов языка, а как показали опыты, человек, определяя вкус продуктов только с помощью рецепторов языка, не отличает даже очищенного яблока от сырого картофеля.",
        "attachments": [],
        "question": {
            "type": "multiple_choice",
            "min_choices": 1,
            "choices": [
                {
                    "id": "1",
                    "text": "1)Человек различает вкус продуктов в большей степени за счёт обоняния, а не рецепторов языка, вот почему, когда обоняние пропадает, пища становится безвкусной, следовательно, богатством вкуса человек обязан своему обонянию"
                },
                {
                    "id": "2",
                    "text": "2) О вкусе известно гораздо больше, чем об обонянии: подобно пахучим химическим соединениям, вещества, передающие нам вкус, растворяются в слюне и дают ощущение вкуса"
                },
                {
                    "id": "3",
                    "text": "3) Богатством  вкуса человек обязан  своему  обонянию:  когда обоняние пропадает, пища становится безвкусной, так как человек различает вкус продуктов в большей степени за счёт обоняния, а не рецепторов языка"
                },
                {
                    "id": "4",
                    "text": "4) Всем богатством того, что называется обонянием, человек обязан своему вкусу"
                },
                {
                    "id": "5",
                    "text": "5) При сильной простуде пища становится безвкусной, так как, будучи реакцией на химические вещества, вкус сродни обонянию"
                }
            ]
        },
        "solution": {
            "correct_variants": [
                [
                    "3",
                    "1"
                ],
                [
                    "1",
                    "3"
                ]
            ]
        },
        "score": 1
    },
    {
        "id": "2",
        "text": "Самостоятельно подберите указательное местоимение, которое должно быть на месте пропуска во втором предложении.(1)Оказывается, всем богатством того, что называется вкусом, человек обязан своему обонянию. (2)<...> объясняется тот факт, что при сильной простуде, когда обоняние на время пропадает, пища становится безвкусной. (3)При простуде мы получаем информацию о вкусе только с помощью рецепторов языка, а как показали опыты, человек, определяя вкус продуктов только с помощью рецепторов языка, не отличает даже очищенного яблока от сырого картофеля.",
        "attachments": [],
        "question": {
            "type": "text",
            "max_length": 30,
            "recommended_length": 20,
            "restriction": "word"
        },
        "solution": {
            "correct": "Этим"
        },
        "score": 1
    },
    {
        "id": "3",
        "text": "Прочитайте фрагмент словарной статьи, в которой приводятся значения слова ПРОДУКТ. Определите значение, в котором это слово употреблено в третьем (3) предложении текста. Выпишите цифру, соответствующую этому значению в приведённом фрагменте словарной статьи. ПРОДУ́КТ, -а, муж.1. Предмет как результат человеческого труда (обработки, переработки, исследования). Продукты производства. Продукты обмена. Продукты перегонки нефти. Книга п. многолетнего труда.2. перен. Следствие, результат, порождение чего-н. (книжн.). Язык п. исторического развития.3. обычно мн. Предметы питания, съестные припасы. Молочные продукты. Запасы продуктов.(1)Оказывается, всем богатством того, что называется вкусом, человек обязан своему обонянию. (2)<...> объясняется тот факт, что при сильной простуде, когда обоняние на время пропадает, пища становится безвкусной. (3)При простуде мы получаем информацию о вкусе только с помощью рецепторов языка, а как показали опыты, человек, определяя вкус продуктов только с помощью рецепторов языка, не отличает даже очищенного яблока от сырого картофеля.",
        "attachments": [],
        "question": {
            "type": "choice",
            "choices": [
                {
                    "id": "1",
                    "text": "1. Предмет как результат человеческого труда (обработки, переработки, исследования). Продукты производства. Продукты обмена. Продукты перегонки нефти. Книга п. многолетнего труда"
                },
                {
                    "id": "2",
                    "text": "2. перен. Следствие, результат, порождение чего-н. (книжн.). Язык п. исторического развития"
                },
                {
                    "id": "3",
                    "text": "3. обычно мн. Предметы питания, съестные припасы. Молочные продукты. Запасы продуктов."
                }
            ]
        },
        "solution": {
            "correct": [
                "3"
            ]
        },
        "score": 1
    },
    {
        "id": "4",
        "text": "В каком слове допущена ошибка в постановке ударения: НЕВЕРНО выделена буква, обозначающая ударный гласный звук? Выпишите это слово. \n заперлА\n углУбить\n граждАнство\n отдАв\n укрепИть",
        "attachments": [],
        "question": {
            "type": "text",
            "max_length": 30,
            "recommended_length": 20,
            "restriction": "word"
        },
        "solution": {
            "correct": "углубить"
        },
        "score": 1
    },
    {
        "id": "5",
        "text": "В одном из приведённых ниже предложений НЕВЕРНО употреблено выделенное слово. Исправьте лексическую ошибку, подобрав к выделенному слову пароним. Запишите подобранное слово.   Стать ДИПЛОМАНТОМ Московской консерватории — большая честь даже для знаменитостей. Длинные и узкие лыжи специально предназначены для ГОНЧЕГО бега. Внезапно до его слуха донёсся ЯВСТВЕННЫЙ звук колокольчика. Я знал и этот монастырь, и это глубокое РЫБНОЕ озеро. Сегодня холодно, так что я НАДЕНУ теплую куртку.",
        "attachments": [],
        "question": {
            "type": "text",
            "max_length": 30,
            "recommended_length": 20,
            "restriction": "word"
        },
        "solution": {
            "correct": "гоночного"
        },
        "score": 1
    },
    {
        "id": "6",
        "text": "Отредактируйте предложение: исправьте лексическую ошибку, исключив лишнее слово. Выпишите это слово.  Температура атмосферного воздуха в феврале была выше нормы, поэтому первоцветы распустились раньше обычного.",
        "attachments": [],
        "question": {
            "type": "text",
            "max_length": 30,
            "recommended_length": 20,
            "restriction": "word"
        },
        "solution": {
            "correct": "атмосферного"
        },
        "score": 1
    },
    {
        "id": "7",
        "text": "В одном из выделенных ниже слов допущена ошибка в образовании формы слова. Исправьте ошибку и запишите слово правильно.\n ЧЕТЫРЬМЯСТАМИ рублями\n ПОЛОЩУЩИЙ бельё\n много ВИШЕН\n БОЛЕЕ ВЫШЕ прыгнуть\n опытные ТРЕНЕРЫ",
        "attachments": [],
        "question": {
            "type": "text",
            "max_length": 30,
            "recommended_length": 20,
            "restriction": "word"
        },
        "solution": {
            "correct_variants": [
                "болеевысоко",
                "выше",
                "высоко"
            ]
        },
        "score": 1
    },
    {
        "id": "8",
        "text": "Установите соответствие между грамматическими ошибками и предложениями, в которых они допущены: к каждой позиции первого столбца подберите соответствующую позицию из второго столбца. ГРАММАТИЧЕСКИЕ ОШИБКИ   ПРЕДЛОЖЕНИЯА) ошибка в построении предложения с однородными членамиБ) неправильное употребление падежной формы существительного с предлогомВ) ошибка в построении предложения с деепричастным оборотомГ) неправильное построение предложения с косвенной речьюД) ошибка в употреблении имени числительного      1) Каждый день я поливал и любовался этими необычными цветами.2) Лингвист Ф.И. Буслаев часто говорил, что убеждён в необходимости основательного преподавания родного языка.3) Пишу вам из деревни, куда заехал вследствие печальным обстоятельствам.4) Отдыхая в кресле, передо мной висит картина \"Март\".5) Выбирая стиль одежды, руководствуйтесь определёнными правилами.6) Тем, кто играет на фортепиано, известны имена великих пианистов.7) Настя спросила, что приедут они к нам.8) При подлёте к комете космический аппарат напоминал готового к сражению рыцаря, который закован в прочные латы.9) Трое дней и ночей не уходили механизаторы с полей, работая в обе смены. Запишите в ответ цифры, расположив их в порядке, соответствующем буквам: AБВГД     ",
        "attachments": [],
        "question": {
            "type": "matching",
            "left": [
                {
                    "id": "A",
                    "text": "А) ошибка в построении предложения с однородными членами"
                },
                {
                    "id": "B",
                    "text": "Б) неправильное употребление падежной формы существительного с предлогом"
                },
                {
                    "id": "C",
                    "text": "В) ошибка в построении предложения с деепричастным оборотом"
                },
                {
                    "id": "D",
                    "text": "Г) неправильное построение предложения с косвенной речью"
                },
                {
                    "id": "E",
                    "text": "Д) ошибка в употреблении имени числительного      "
                }
            ],
            "choices": [
                {
                    "id": "1",
                    "text": "1) Каждый день я поливал и любовался этими необычными цветами"
                },
                {
                    "id": "2",
                    "text": "2) Лингвист Ф.И. Буслаев часто говорил, что убеждён в необходимости основательного преподавания родного языка"
                },
                {
                    "id": "3",
                    "text": "3) Пишу вам из деревни, куда заехал вследствие печальным обстоятельствам"
                },
                {
                    "id": "4",
                    "text": "4) Отдыхая в кресле, передо мной висит картина \"Март\""
                },
                {
                    "id": "5",
                    "text": "5) Выбирая стиль одежды, руководствуйтесь определёнными правилами"
                },
                {
                    "id": "6",
                    "text": "6) Тем, кто играет на фортепиано, известны имена великих пианистов"
                },
                {
                    "id": "7",
                    "text": "7) Настя спросила, что приедут они к нам"
                },
                {
                    "id": "8",
                    "text": "8) При подлёте к комете космический аппарат напоминал готового к сражению рыцаря, который закован в прочные латы"
                },
                {
                    "id": "9",
                    "text": "9) Трое дней и ночей не уходили механизаторы с полей, работая в обе смены. "
                }
            ]
        },
        "solution": {
            "correct": {
                "A": "1",
                "B": "3",
                "C": "4",
                "D": "7",
                "E": "9"
            }
        },
        "score": 5
    },
    {
        "id": "9",
        "text": "Укажите варианты ответов, в которых во всех словах одного ряда пропущена безударная проверяемая гласная корня. Запишите номера ответов. 1) закл..нать, р..акция, пол..гать2) проф..риентация, д..брота, в..теран3) загл..денье, прим..рять (галстук), п..левая (кухня)4) вн..мательный, д..пломат, през..дент5) г..рода, насм..хаться, скр..пучая",
        "attachments": [],
        "question": {
            "type": "multiple_choice",
            "min_choices": 1,
            "choices": [
                {
                    "id": "1",
                    "text": "1) закл..нать, р..акция, пол..гать"
                },
                {
                    "id": "2",
                    "text": "2) проф..риентация, д..брота, в..теран"
                },
                {
                    "id": "3",
                    "text": "3) загл..денье, прим..рять (галстук), п..левая (кухня)"
                },
                {
                    "id": "4",
                    "text": "4) вн..мательный, д..пломат, през..дент"
                },
                {
                    "id": "5",
                    "text": "5) г..рода, насм..хаться, скр..пучая"
                }
            ]
        },
        "solution": {
            "correct_variants": [
                [
                    "3",
                    "5"
                ],
                [
                    "5",
                    "3"
                ]
            ]
        },
        "score": 1
    },
    {
        "id": "10",
        "text": "Укажите варианты ответов, в которых во всех  словах одного ряда пропущена одна и та же буква. Запишите номера ответов.   1) пр..глушить, пр..дставить, пр..творить (дверь);2) и..гнать, не..гораемый, и..менить;3) пред..нвестиционный, под..тожить, за..скрить;4) непр..будный, в..скликнуть, в..ткнуть;5) на..треснутый, по..крадываться, по..расти.",
        "attachments": [],
        "question": {
            "type": "multiple_choice",
            "min_choices": 1,
            "choices": [
                {
                    "id": "1",
                    "text": "1) пр..глушить, пр..дставить, пр..творить (дверь)"
                },
                {
                    "id": "2",
                    "text": "2) и..гнать, не..гораемый, и..менить"
                },
                {
                    "id": "3",
                    "text": "3) пред..нвестиционный, под..тожить, за..скрить"
                },
                {
                    "id": "4",
                    "text": "4) непр..будный, в..скликнуть, в..ткнуть"
                },
                {
                    "id": "5",
                    "text": "5) на..треснутый, по..крадываться, по..расти"
                }
            ]
        },
        "solution": {
            "correct_variants": [
                [
                    "4",
                    "5"
                ],
                [
                    "5",
                    "4"
                ]
            ]
        },
        "score": 1
    },
    {
        "id": "11",
        "text": "Укажите варианты ответов, в которых в обоих словах одного ряда пропущена одна и та же буква. Запишите номера ответов.    1) успока..вая, врем..ни 2) ноздр..ватый, француж..нка3) преодол..вающий, горл..нка4) локт..вой, желт..зна5) недоум..вать, утр..чко",
        "attachments": [],
        "question": {
            "type": "multiple_choice",
            "min_choices": 1,
            "choices": [
                {
                    "id": "1",
                    "text": "1) успока..вая, врем..ни"
                },
                {
                    "id": "2",
                    "text": "2) ноздр..ватый, француж..нка"
                },
                {
                    "id": "3",
                    "text": "3) преодол..вающий, горл..нка"
                },
                {
                    "id": "4",
                    "text": "4) локт..вой, желт..зна"
                },
                {
                    "id": "5",
                    "text": "5) недоум..вать, утр..чко"
                }
            ]
        },
        "solution": {
            "correct_variants": [
                [
                    "2",
                    "5"
                ],
                [
                    "5",
                    "2"
                ]
            ]
        },
        "score": 1
    },
    {
        "id": "12",
        "text": "Укажите варианты ответов, в которых во всех  словах одного ряда пропущена одна и та же буква. Запишите номера ответов.1) произнос..шь, слыш..мый2) относ..шься, надума..шь3) засмотр..шься, реша..мый4) невид..мый, разгон..шься5) раска...ться, найд..нный",
        "attachments": [],
        "question": {
            "type": "multiple_choice",
            "min_choices": 1,
            "choices": [
                {
                    "id": "1",
                    "text": "1) произнос..шь, слыш..мый"
                },
                {
                    "id": "2",
                    "text": "2) относ..шься, надума..шь"
                },
                {
                    "id": "3",
                    "text": "3) засмотр..шься, реша..мый"
                },
                {
                    "id": "4",
                    "text": "4) невид..мый, разгон..шься"
                },
                {
                    "id": "5",
                    "text": "5) раска...ться, найд..нный"
                }
            ]
        },
        "solution": {
            "correct_variants": [
                [
                    "1",
                    "4"
                ],
                [
                    "4",
                    "1"
                ]
            ]
        },
        "score": 1
    },
    {
        "id": "13",
        "text": "Определите предложение, в котором НЕ со словом пишется СЛИТНО. Раскройте скобки и выпишите это слово. Мне всегда (не)хватало прилежности.В тишину, еще никем (не)потревоженную, врывается шорох камней. Настала ночь, никто во граде очей бессонных (не)смыкал.Тянутся по Волге нагруженные арбузами баркасы с (не)высокими бортами.Солнце, ещё (не)скрытое облаками, освещает мрачную жёлто-лиловую тучу.",
        "attachments": [],
        "question": {
            "type": "text",
            "max_length": 30,
            "recommended_length": 20,
            "restriction": "word"
        },
        "solution": {
            "correct": "невысокими"
        },
        "score": 1
    },
    {
        "id": "14",
        "text": "Определите предложение, в котором оба выделенных слова пишутся СЛИТНО. Раскройте скобки и выпишите эти два слова. В)СЛЕД за холодными осенними дождями пришли заморозки, (ОТ)ЧЕГО в посёлке стало холодно и неуютно.Трудно представить, ЧТО(БЫ) случилось с нами, если бы не помощь родителей, а ТАК(ЖЕ) поддержка друзей.(НЕ)СМОТРЯ на вечную занятость, я отправился (НА)ВСТРЕЧУ со школьными товарищами.(В)ВИДУ густого тумана все рейсы были отменены, и нам пришлось (В)ТЕЧЕНИЕ двух суток дожидаться лётной погоды(В)ЗАКЛЮЧЕНИЕ оратор повысил голос (И)ТАК торжественно закончил речь, что зал взорвался аплодисментами.",
        "attachments": [],
        "question": {
            "type": "text",
            "max_length": 30,
            "recommended_length": 20,
            "restriction": "word"
        },
        "solution": {
            "correct_variants": [
                "вследотчего",
                "отчеговслед"
            ]
        },
        "score": 1
    },
    {
        "id": "15",
        "score": 1,
        "text": "Укажите все цифры, на месте которых пишется НН.Цифры укажите в порядке возрастания. Леруа лукавит, как всякий исти(1)ый француз, утверждая, что всё это лишь художестве(2)ое произведение, а многие характеры открове(3)о выдума(4)ы.",
        "attachments": [],
        "question": {
            "type": "multiple_choice",
            "choices": [
                {
                    "id": "1",
                    "placeholder": "(1)"
                },
                {
                    "id": "2",
                    "placeholder": "(2)"
                },
                {
                    "id": "3",
                    "placeholder": "(3)"
                },
                {
                    "id": "4",
                    "placeholder": "(4)"
                }
            ],
            "min_choices": 1
        },
        "solution": {
            "correct": [
                "1",
                "2",
                "3"
            ]
        }
    },
    {
        "id": "16",
        "text": "Расставьте знаки препинания. Укажите два предложения, в которых нужно поставить ОДНУ запятую. Запишите номера этих предложений. 1) Учитель наш слыл радикалом и бранил за легкомыслие не только Пифагора но даже Лейбница и Ньютона.2) Семён Иванович брал по порциям или одни щи с пирогом или одну говядину.3) Трактирщик то помогал некоторым то отбегал в сторону и всё командовал критиковал.4) В комнате Риты окна были открыты настежь и пахло яблоками.5) Мать положила в мешок хлеба и соли и сахара.",
        "attachments": [],
        "question": {
            "type": "multiple_choice",
            "min_choices": 1,
            "choices": [
                {
                    "id": "1",
                    "text": "1) Учитель наш слыл радикалом и бранил за легкомыслие не только Пифагора но даже Лейбница и Ньютона"
                },
                {
                    "id": "2",
                    "text": "2) Семён Иванович брал по порциям или одни щи с пирогом или одну говядину"
                },
                {
                    "id": "3",
                    "text": "3) Трактирщик то помогал некоторым то отбегал в сторону и всё командовал критиковал"
                },
                {
                    "id": "4",
                    "text": "4) В комнате Риты окна были открыты настежь и пахло яблоками"
                },
                {
                    "id": "5",
                    "text": "5) Мать положила в мешок хлеба и соли и сахара"
                }
            ]
        },
        "solution": {
            "correct_variants": [
                [
                    "1",
                    "2"
                ],
                [
                    "2",
                    "1"
                ]
            ]
        },
        "score": 2
    },
    {
        "id": "17",
        "score": 1,
        "text": "Расставьте все знаки препинания: укажите цифру(-ы), на месте которой(-ых) в предложении должна(-ы) стоять запятая(-ые). На картине будут лишь (1) омытый дождём (2) мокрый луг под огромным небом, несколько деревьев да (3) бегущие по влажной траве (4) тени сизых туч (5) гонимых ветром.",
        "attachments": [],
        "question": {
            "type": "multiple_choice",
            "choices": [
                {
                    "id": "1",
                    "placeholder": "(1)"
                },
                {
                    "id": "2",
                    "placeholder": "(2)"
                },
                {
                    "id": "3",
                    "placeholder": "(3)"
                },
                {
                    "id": "4",
                    "placeholder": "(4)"
                },
                {
                    "id": "5",
                    "placeholder": "(5)"
                }
            ],
            "min_choices": 1
        },
        "solution": {
            "correct": [
                "5"
            ]
        }
    },
    {
        "id": "18",
        "score": 1,
        "text": "Расставьте все недостающие знаки препинания: укажите цифру(-ы), на месте которой(-ых) в предложении должна(-ы) стоять запятая(-ые). Если язык человека вял, тяжёл, сбивчив, бессилен, то таков (1) вероятно (2) и его ум, ибо мыслит человек (3) как известно (4) только с помощью языка.",
        "attachments": [],
        "question": {
            "type": "multiple_choice",
            "choices": [
                {
                    "id": "1",
                    "placeholder": "(1)"
                },
                {
                    "id": "2",
                    "placeholder": "(2)"
                },
                {
                    "id": "3",
                    "placeholder": "(3)"
                },
                {
                    "id": "4",
                    "placeholder": "(4)"
                }
            ],
            "min_choices": 1
        },
        "solution": {
            "correct": [
                "1",
                "2",
                "3",
                "4"
            ]
        }
    },
    {
        "id": "19",
        "score": 1,
        "text": "Расставьте все знаки препинания: укажите цифру(-ы), на месте которой(-ых) в предложении должна(-ы) стоять запятая(-ые). Каменные дорожки (1) извилистые линии (2) которых (3) символизируют поток энергии (4) приобретают особое значение в японском саду.",
        "attachments": [],
        "question": {
            "type": "multiple_choice",
            "choices": [
                {
                    "id": "1",
                    "placeholder": "(1)"
                },
                {
                    "id": "2",
                    "placeholder": "(2)"
                },
                {
                    "id": "3",
                    "placeholder": "(3)"
                },
                {
                    "id": "4",
                    "placeholder": "(4)"
                }
            ],
            "min_choices": 1
        },
        "solution": {
            "correct_variants": [
                [
                    "1",
                    "4"
                ],
                [
                    "4",
                    "1"
                ]
            ]
        }
    },
    {
        "id": "20",
        "score": 1,
        "text": "Расставьте все знаки препинания: укажите цифру(-ы), на месте которой(-ых) в предложении должна(-ы) стоять запятая(-ые). Когда Иван Аристархович появлялся в дверях гримёрной (1) он привычно наклонялся (2) и (3) поэтому у всех актёров складывалось впечатление (4) что их художественный руководитель очень высокого роста (5) хотя на самом деле просто дверной проём был достаточно низкий.",
        "attachments": [],
        "question": {
            "type": "multiple_choice",
            "choices": [
                {
                    "id": "1",
                    "placeholder": "(1)"
                },
                {
                    "id": "2",
                    "placeholder": "(2)"
                },
                {
                    "id": "3",
                    "placeholder": "(3)"
                },
                {
                    "id": "4",
                    "placeholder": "(4)"
                },
                {
                    "id": "5",
                    "placeholder": "(5)"
                }
            ],
            "min_choices": 1
        },
        "solution": {
            "correct": [
                "1",
                "2",
                "4",
                "5"
            ]
        }
    },
    {
        "id": "21",
        "score": 1,
        "text": "Найдите предложения, в которых запятые ставятся в соответствии с одним и тем же правилом пунктуации. Запишите номера этих предложений.  1) Зелень, одаривая съедобными травами и небывалыми ароматами, в июле уже вовсю цветет. 2) Небосклон голубой и чистый, время от времени проплывают по нему пушистые облака. 3) И вдруг неожиданно жаркое летнее солнце сменяют надвигающиеся тучи. 4) Только что было солнце - теперь его поглотила грозная тьма. 5) Сильные порывы ветра, с каждым разом усиливаясь, готовы сорвать ветви с макушек деревьев на своем пути. 6) Гроза стихает так же неожиданно, как и началась. 7) Впереди еще долгие жаркие, знойные и просто теплые приятные деньки.",
        "attachments": [],
        "question": {
            "type": "multiple_choice",
            "choices": [
                {
                    "id": "1",
                    "link": "(1)"
                },
                {
                    "id": "2",
                    "link": "(2)"
                },
                {
                    "id": "3",
                    "link": "(3)"
                },
                {
                    "id": "4",
                    "link": "(4)"
                },
                {
                    "id": "5",
                    "link": "(5)"
                },
                {
                    "id": "6",
                    "link": "(6)"
                },
                {
                    "id": "7",
                    "link": "(7)"
                }
            ],
            "min_choices": 1
        },
        "solution": {
            "correct": [
                "1",
                "5"
            ]
        }
    },
    {
        "id": "22",
        "text": "Какие из высказываний соответствуют содержанию текста? Укажите номера ответов в возрастающем порядке. 1)Жил однажды чудак… (2)Он был очень богат и имел всё из вещей, что человек может себе только пожелать. (3)Дом его украшали мраморные лестницы, персидские ковры и золочёная мебель. (4)В саду, окружавшем этот роскошный дворец, благоухали цветы, били прохладные фонтаны, заморские птицы услаждали слух своим причудливым пением.(5)Однако, несмотря на внешнее благополучие, наш чудак чувствовал, что ему не хватает чего-то самого главного, чего он даже и назвать не мог. (6)Человек решительный и отважный, он так много мог, он почти всё смел, но он не знал такого, к чему можно стремиться, и жизнь казалась ему бессмысленной и мёртвой. (7)Ничто не радовало его, и богатство, всё более умножаясь, постепенно становилось для него горестным бременем.(8)Тогда он пошёл к одной старой женщине, которая пестовала свою древнюю мудрость в пещере дремлющей огненной горы. (9)Чудак рассказал ей о своей беде, и старуха ответила ему: (10)«Отправляйся в большой мир, чтобы найти пропавшее. (11) Твоё несчастье велико: тебе не хватает главного, и, пока ты его не найдёшь, жизнь для тебя будет бедой и пыткой».(12)Эта сказка всегда приходит мне на ум, когда я думаю о современном мире и его духовном кризисе. (13)Как богато человечество благами низшего порядка! (14) И будет делаться всё богаче. (15)Пространство будет побеждено, таинственные формы материи будут открыты, и ими овладеют. (16)Всё новые и новые инструменты, средства и возможности будут предоставлены человеку в распоряжение, но главное отсутствует.(17)«Как» земной жизни развивается безостановочно, но «зачем» – незаметно утрачивается. (18)Это так, как если бы человек, который страдает рассеянностью, играл в шахматы и выработал для себя дальновидный, сложный план, осуществление которого уже наполовину завершено, и вдруг он забывает свой план. (19)«Прекрасно! (20)Но для чего я всё это предпринимал? (21)Чего я, собственно, этим хотел?!» (22)Давайте вспомним о естественно-научных и технических изобретениях последнего столетия. (23)Электричество, динамит, культуры бактерий, железобетон, самолёт, радио, расщепление атома. (24)Само по себе этого довольно и сверхдостаточно, чтобы создать нечто великое. (25)Выход на такой заоблачный уровень, на такие пути предполагает наличие всеобъемлющего, окрылённого, дальновидного, целенаправленного сознания, развитие искусства, несущего огромную духовно-воспитательную силу. (26)Жизнь без смысла при таких условиях становится опаснее, чем когда бы то ни было. (27)Возможности созидания могут стать средствами всеобщего разрушения. (28)Ведь сами по себе они не хороши и не плохи, они лишь мощная, неопределённая «возможность», дремлющая огненная гора, непредсказуемая и своенравная во всём.(29)Современное человечество должно хотя бы интуитивно чувствовать, «куда» оно идёт, «зачем» ему даны эти возможности, «как» надо употребить, применить всё это, чтобы творческий путь познания не превратился в путь руин. (30)Что получится, если кучка лишённых духовных корней и нравственно разнузданных «завоевателей мира» начнёт возиться с инструментами современной химии, техники и науки?(31)Несчастье современного человека велико, ибо ему не хватает главного – смысла жизни. (32)Он должен отправиться на поиски. (33)И пока он не найдёт главного, беды и опасности будут подстерегать всё чаще и чаще. (34)Несмотря на всю мощь его разума и широту его возможностей. (По И.А. Ильину*)*Иван Александрович Ильин (1883–1954) – известный религиозный философ, писатель и публицист русского зарубежья.",
        "attachments": [],
        "question": {
            "type": "multiple_choice",
            "min_choices": 1,
            "choices": [
                {
                    "id": "1",
                    "text": "1) Счастье заключается не в материальных благах, а в обретении смысла жизни"
                },
                {
                    "id": "2",
                    "text": "2) Если человечество не задумается о смысле жизни, познание может оказаться разрушительным для современного мира"
                },
                {
                    "id": "3",
                    "text": "3) Вопрос о смысле жизни может представлять серьёзную опасность для современного человека"
                },
                {
                    "id": "4",
                    "text": "4) Человечество непрерывно движется вперёд, к новым открытиям и свершениям"
                },
                {
                    "id": "5",
                    "text": "5) Все богатые люди пытаются найти смысл жизни среди роскоши"
                }
            ]
        },
        "solution": {
            "correct": [
                "1",
                "2",
                "4"
            ]
        },
        "score": 1
    },
    {
        "id": "23",
        "text": "Какие из перечисленных утверждений являются верными? Укажите номера ответов в порядке возрастания. 1)Жил однажды чудак… (2)Он был очень богат и имел всё из вещей, что человек может себе только пожелать. (3)Дом его украшали мраморные лестницы, персидские ковры и золочёная мебель. (4)В саду, окружавшем этот роскошный дворец, благоухали цветы, били прохладные фонтаны, заморские птицы услаждали слух своим причудливым пением.(5)Однако, несмотря на внешнее благополучие, наш чудак чувствовал, что ему не хватает чего-то самого главного, чего он даже и назвать не мог. (6)Человек решительный и отважный, он так много мог, он почти всё смел, но он не знал такого, к чему можно стремиться, и жизнь казалась ему бессмысленной и мёртвой. (7)Ничто не радовало его, и богатство, всё более умножаясь, постепенно становилось для него горестным бременем.(8)Тогда он пошёл к одной старой женщине, которая пестовала свою древнюю мудрость в пещере дремлющей огненной горы. (9)Чудак рассказал ей о своей беде, и старуха ответила ему: (10)«Отправляйся в большой мир, чтобы найти пропавшее. (11) Твоё несчастье велико: тебе не хватает главного, и, пока ты его не найдёшь, жизнь для тебя будет бедой и пыткой».(12)Эта сказка всегда приходит мне на ум, когда я думаю о современном мире и его духовном кризисе. (13)Как богато человечество благами низшего порядка! (14) И будет делаться всё богаче. (15)Пространство будет побеждено, таинственные формы материи будут открыты, и ими овладеют. (16)Всё новые и новые инструменты, средства и возможности будут предоставлены человеку в распоряжение, но главное отсутствует.(17)«Как» земной жизни развивается безостановочно, но «зачем» – незаметно утрачивается. (18)Это так, как если бы человек, который страдает рассеянностью, играл в шахматы и выработал для себя дальновидный, сложный план, осуществление которого уже наполовину завершено, и вдруг он забывает свой план. (19)«Прекрасно! (20)Но для чего я всё это предпринимал? (21)Чего я, собственно, этим хотел?!» (22)Давайте вспомним о естественно-научных и технических изобретениях последнего столетия. (23)Электричество, динамит, культуры бактерий, железобетон, самолёт, радио, расщепление атома. (24)Само по себе этого довольно и сверхдостаточно, чтобы создать нечто великое. (25)Выход на такой заоблачный уровень, на такие пути предполагает наличие всеобъемлющего, окрылённого, дальновидного, целенаправленного сознания, развитие искусства, несущего огромную духовно-воспитательную силу. (26)Жизнь без смысла при таких условиях становится опаснее, чем когда бы то ни было. (27)Возможности созидания могут стать средствами всеобщего разрушения. (28)Ведь сами по себе они не хороши и не плохи, они лишь мощная, неопределённая «возможность», дремлющая огненная гора, непредсказуемая и своенравная во всём.(29)Современное человечество должно хотя бы интуитивно чувствовать, «куда» оно идёт, «зачем» ему даны эти возможности, «как» надо употребить, применить всё это, чтобы творческий путь познания не превратился в путь руин. (30)Что получится, если кучка лишённых духовных корней и нравственно разнузданных «завоевателей мира» начнёт возиться с инструментами современной химии, техники и науки?(31)Несчастье современного человека велико, ибо ему не хватает главного – смысла жизни. (32)Он должен отправиться на поиски. (33)И пока он не найдёт главного, беды и опасности будут подстерегать всё чаще и чаще. (34)Несмотря на всю мощь его разума и широту его возможностей. (По И.А. Ильину*)*Иван Александрович Ильин (1883–1954) – известный религиозный философ, писатель и публицист русского зарубежья.",
        "attachments": [],
        "question": {
            "type": "multiple_choice",
            "min_choices": 1,
            "choices": [
                {
                    "id": "1",
                    "text": "1) Предложения 3–4 содержат описание"
                },
                {
                    "id": "2",
                    "text": "2) Предложение 15 содержит пояснение к тому, о чём говорится в предложениях 13 и 14"
                },
                {
                    "id": "3",
                    "text": "3) Предложения 22–24 содержат описание"
                },
                {
                    "id": "4",
                    "text": "4) Преобладающий тип текста—описание"
                },
                {
                    "id": "5",
                    "text": "5) В предложениях 29–30 представлено рассуждение"
                }
            ]
        },
        "solution": {
            "correct": [
                "1",
                "2",
                "5"
            ]
        },
        "score": 1
    },
    {
        "id": "24",
        "text": "Из предложения 28  выпишите  антонимы.(1)Жил однажды чудак…  Он был очень богат и имел всё из вещей, что человек может себе только пожелать. (3)Дом его украшали мраморные лестницы, персидские ковры и золочёная мебель. (4)В саду, окружавшем этот роскошный дворец, благоухали цветы, били прохладные фонтаны, заморские птицы услаждали слух своим причудливым пением.(5)Однако, несмотря на внешнее благополучие, наш чудак чувствовал, что ему не хватает чего-то самого главного, чего он даже и назвать не мог. (6)Человек решительный и отважный, он так много мог, он почти всё смел, но он не знал такого, к чему можно стремиться, и жизнь казалась ему бессмысленной и мёртвой. (7)Ничто не радовало его, и богатство, всё более умножаясь, постепенно становилось для него горестным бременем.(8)Тогда он пошёл к одной старой женщине, которая пестовала свою древнюю мудрость в пещере дремлющей огненной горы. (9)Чудак рассказал ей о своей беде, и старуха ответила ему: (10)«Отправляйся в большой мир, чтобы найти пропавшее. (11) Твоё несчастье велико: тебе не хватает главного, и, пока ты его не найдёшь, жизнь для тебя будет бедой и пыткой».(12)Эта сказка всегда приходит мне на ум, когда я думаю о современном мире и его духовном кризисе. (13)Как богато человечество благами низшего порядка! (14) И будет делаться всё богаче. (15)Пространство будет побеждено, таинственные формы материи будут открыты, и ими овладеют. (16)Всё новые и новые инструменты, средства и возможности будут предоставлены человеку в распоряжение, но главное отсутствует.(17)«Как» земной жизни развивается безостановочно, но «зачем» – незаметно утрачивается. (18)Это так, как если бы человек, который страдает рассеянностью, играл в шахматы и выработал для себя дальновидный, сложный план, осуществление которого уже наполовину завершено, и вдруг он забывает свой план. (19)«Прекрасно! (20)Но для чего я всё это предпринимал? (21)Чего я, собственно, этим хотел?!» (22)Давайте вспомним о естественно-научных и технических изобретениях последнего столетия. (23)Электричество, динамит, культуры бактерий, железобетон, самолёт, радио, расщепление атома. (24)Само по себе этого довольно и сверхдостаточно, чтобы создать нечто великое. (25)Выход на такой заоблачный уровень, на такие пути предполагает наличие всеобъемлющего, окрылённого, дальновидного, целенаправленного сознания, развитие искусства, несущего огромную духовно-воспитательную силу. (26)Жизнь без смысла при таких условиях становится опаснее, чем когда бы то ни было. (27)Возможности созидания могут стать средствами всеобщего разрушения. (28)Ведь сами по себе они не хороши и не плохи, они лишь мощная, неопределённая «возможность», дремлющая огненная гора, непредсказуемая и своенравная во всём.(29)Современное человечество должно хотя бы интуитивно чувствовать, «куда» оно идёт, «зачем» ему даны эти возможности, «как» надо употребить, применить всё это, чтобы творческий путь познания не превратился в путь руин. (30)Что получится, если кучка лишённых духовных корней и нравственно разнузданных «завоевателей мира» начнёт возиться с инструментами современной химии, техники и науки?(31)Несчастье современного человека велико, ибо ему не хватает главного – смысла жизни. (32)Он должен отправиться на поиски. (33)И пока он не найдёт главного, беды и опасности будут подстерегать всё чаще и чаще. (34)Несмотря на всю мощь его разума и широту его возможностей. (По И.А. Ильину*)*Иван Александрович Ильин (1883–1954) – известный религиозный философ, писатель и публицист русского зарубежья.",
        "attachments": [],
        "question": {
            "type": "text",
            "max_length": 30,
            "recommended_length": 20,
            "restriction": "word"
        },
        "solution": {
            "correct_variants": [
                "нехорошинеплохи",
                "хорошиплохи"
            ]
        },
        "score": 1
    },
    {
        "id": "25",
        "score": 1,
        "text": "Среди предложений 1–7 найдите такое(-ие), которое(-ые) связано(-ы) с предыдущим при помощи притяжательного местоимения. Напишите номер(-а) этого(-их) предложения(-ий). (1) Жил однажды чудак… (2)Он был очень богат и имел всё из вещей, что человек может себе только пожелать. (3)Дом его украшали мраморные лестницы, персидские ковры и золочёная мебель. (4)В саду, окружавшем этот роскошный дворец, благоухали цветы, били прохладные фонтаны, заморские птицы услаждали слух своим причудливым пением.(5)Однако, несмотря на внешнее благополучие, наш чудак чувствовал, что ему не хватает чего-то самого главного, чего он даже и назвать не мог. (6)Человек решительный и отважный, он так много мог, он почти всё смел, но он не знал такого, к чему можно стремиться, и жизнь казалась ему бессмысленной и мёртвой. (7)Ничто не радовало его, и богатство, всё более умножаясь, постепенно становилось для него горестным бременем.(8)Тогда он пошёл к одной старой женщине, которая пестовала свою древнюю мудрость в пещере дремлющей огненной горы. (9)Чудак рассказал ей о своей беде, и старуха ответила ему: (10)«Отправляйся в большой мир, чтобы найти пропавшее. (11) Твоё несчастье велико: тебе не хватает главного, и, пока ты его не найдёшь, жизнь для тебя будет бедой и пыткой».(12)Эта сказка всегда приходит мне на ум, когда я думаю о современном мире и его духовном кризисе. (13)Как богато человечество благами низшего порядка! (14) И будет делаться всё богаче. (15)Пространство будет побеждено, таинственные формы материи будут открыты, и ими овладеют. (16)Всё новые и новые инструменты, средства и возможности будут предоставлены человеку в распоряжение, но главное отсутствует.(17)«Как» земной жизни развивается безостановочно, но «зачем» – незаметно утрачивается. (18)Это так, как если бы человек, который страдает рассеянностью, играл в шахматы и выработал для себя дальновидный, сложный план, осуществление которого уже наполовину завершено, и вдруг он забывает свой план. (19)«Прекрасно! (20)Но для чего я всё это предпринимал? (21)Чего я, собственно, этим хотел?!» (22)Давайте вспомним о естественно-научных и технических изобретениях последнего столетия. (23)Электричество, динамит, культуры бактерий, железобетон, самолёт, радио, расщепление атома. (24)Само по себе этого довольно и сверхдостаточно, чтобы создать нечто великое. (25)Выход на такой заоблачный уровень, на такие пути предполагает наличие всеобъемлющего, окрылённого, дальновидного, целенаправленного сознания, развитие искусства, несущего огромную духовно-воспитательную силу. (26)Жизнь без смысла при таких условиях становится опаснее, чем когда бы то ни было. (27)Возможности созидания могут стать средствами всеобщего разрушения. (28)Ведь сами по себе они не хороши и не плохи, они лишь мощная, неопределённая «возможность», дремлющая огненная гора, непредсказуемая и своенравная во всём.(29)Современное человечество должно хотя бы интуитивно чувствовать, «куда» оно идёт, «зачем» ему даны эти возможности, «как» надо употребить, применить всё это, чтобы творческий путь познания не превратился в путь руин. (30)Что получится, если кучка лишённых духовных корней и нравственно разнузданных «завоевателей мира» начнёт возиться с инструментами современной химии, техники и науки?(31)Несчастье современного человека велико, ибо ему не хватает главного – смысла жизни. (32)Он должен отправиться на поиски. (33)И пока он не найдёт главного, беды и опасности будут подстерегать всё чаще и чаще. (34)Несмотря на всю мощь его разума и широту его возможностей. (По И.А. Ильину*)*Иван Александрович Ильин (1883–1954) – известный религиозный философ, писатель и публицист русского зарубежья.",
        "attachments": [],
        "question": {
            "type": "multiple_choice",
            "choices": [
                {
                    "id": "1",
                    "link": "(1)"
                },
                {
                    "id": "2",
                    "link": "(2)"
                },
                {
                    "id": "3",
                    "link": "(3)"
                },
                {
                    "id": "4",
                    "link": "(4)"
                },
                {
                    "id": "5",
                    "link": "(5)"
                },
                {
                    "id": "6",
                    "link": "(6)"
                },
                {
                    "id": "7",
                    "link": "(7)"
                },
                {
                    "id": "8",
                    "link": "(8)"
                },
                {
                    "id": "9",
                    "link": "(9)"
                },
                {
                    "id": "10",
                    "link": "(10)"
                },
                {
                    "id": "11",
                    "link": "(11)"
                },
                {
                    "id": "12",
                    "link": "(12)"
                },
                {
                    "id": "13",
                    "link": "(13)"
                },
                {
                    "id": "14",
                    "link": "(14)"
                },
                {
                    "id": "15",
                    "link": "(15)"
                },
                {
                    "id": "16",
                    "link": "(16)"
                },
                {
                    "id": "17",
                    "link": "(17)"
                },
                {
                    "id": "18",
                    "link": "(18)"
                },
                {
                    "id": "19",
                    "link": "(19)"
                },
                {
                    "id": "20",
                    "link": "(20)"
                },
                {
                    "id": "21",
                    "link": "(21)"
                },
                {
                    "id": "22",
                    "link": "(22)"
                },
                {
                    "id": "23",
                    "link": "(23)"
                },
                {
                    "id": "24",
                    "link": "(24)"
                },
                {
                    "id": "25",
                    "link": "(25)"
                },
                {
                    "id": "26",
                    "link": "(26)"
                },
                {
                    "id": "27",
                    "link": "(27)"
                },
                {
                    "id": "28",
                    "link": "(28)"
                },
                {
                    "id": "29",
                    "link": "(29)"
                },
                {
                    "id": "30",
                    "link": "(30)"
                },
                {
                    "id": "31",
                    "link": "(31)"
                },
                {
                    "id": "32",
                    "link": "(32)"
                },
                {
                    "id": "33",
                    "link": "(33)"
                },
                {
                    "id": "34",
                    "link": "(34)"
                },
                {
                    "id": "35",
                    "link": "(35)"
                },
                {
                    "id": "36",
                    "link": "(36)"
                },
                {
                    "id": "37",
                    "link": "(37)"
                },
                {
                    "id": "38",
                    "link": "(38)"
                },
                {
                    "id": "39",
                    "link": "(39)"
                },
                {
                    "id": "40",
                    "link": "(40)"
                },
                {
                    "id": "41",
                    "link": "(41)"
                }
            ],
            "min_choices": 1
        },
        "solution": {
            "correct": [
                "3"
            ]
        }
    },
    {
        "id": "26",
        "text": "Прочитайте фрагмент рецензии. В нём рассматриваются языковые особенности текста. Некоторые термины, использованные в рецензии, пропущены. Вставьте на места пропусков цифры, соответствующие номеру термина из списка.  Отношение И. А. Ильина к поиску смысла жизни помогает подчеркнуть такой стилистический приём, как (А)_____ («новые» в предложении 16, «главное» в предложениях 16, 31, 33, «чаще» в предложении 33). Чтобы точнее передать ход своей мысли, писатель умело применяет синтаксические средства выразительности, например (Б)_____ (предложения 13–14, 33, 34) и (В)_____ (предложения 13, 19). Образность авторской речи придают яркие тропы, в частности (Г)_____ («они лишь… огненная гора» в предложении 28, «путь руин» в предложении 29). Список терминов1) парцелляция2) метафора(-ы)3) инверсия4) лексический повтор5) риторические вопросы6) гипербола7) сравнение(-я)8) риторические восклицания9) книжная лексика Запишите в ответ цифры, расположив их в порядке, соответствующем буквам: AБВГ    (1)Жил однажды чудак… (2)Он был очень богат и имел всё из вещей, что человек может себе только пожелать. (3)Дом его украшали мраморные лестницы, персидские ковры и золочёная мебель. (4)В саду, окружавшем этот роскошный дворец, благоухали цветы, били прохладные фонтаны, заморские птицы услаждали слух своим причудливым пением.(5)Однако, несмотря на внешнее благополучие, наш чудак чувствовал, что ему не хватает чего-то самого главного, чего он даже и назвать не мог. (6)Человек решительный и отважный, он так много мог, он почти всё смел, но он не знал такого, к чему можно стремиться, и жизнь казалась ему бессмысленной и мёртвой. (7)Ничто не радовало его, и богатство, всё более умножаясь, постепенно становилось для него горестным бременем.(8)Тогда он пошёл к одной старой женщине, которая пестовала свою древнюю мудрость в пещере дремлющей огненной горы. (9)Чудак рассказал ей о своей беде, и старуха ответила ему: (10)«Отправляйся в большой мир, чтобы найти пропавшее. (11) Твоё несчастье велико: тебе не хватает главного, и, пока ты его не найдёшь, жизнь для тебя будет бедой и пыткой».(12)Эта сказка всегда приходит мне на ум, когда я думаю о современном мире и его духовном кризисе. (13)Как богато человечество благами низшего порядка! (14) И будет делаться всё богаче. (15)Пространство будет побеждено, таинственные формы материи будут открыты, и ими овладеют. (16)Всё новые и новые инструменты, средства и возможности будут предоставлены человеку в распоряжение, но главное отсутствует.(17)«Как» земной жизни развивается безостановочно, но «зачем» – незаметно утрачивается. (18)Это так, как если бы человек, который страдает рассеянностью, играл в шахматы и выработал для себя дальновидный, сложный план, осуществление которого уже наполовину завершено, и вдруг он забывает свой план. (19)«Прекрасно! (20)Но для чего я всё это предпринимал? (21)Чего я, собственно, этим хотел?!» (22)Давайте вспомним о естественно-научных и технических изобретениях последнего столетия. (23)Электричество, динамит, культуры бактерий, железобетон, самолёт, радио, расщепление атома. (24)Само по себе этого довольно и сверхдостаточно, чтобы создать нечто великое. (25)Выход на такой заоблачный уровень, на такие пути предполагает наличие всеобъемлющего, окрылённого, дальновидного, целенаправленного сознания, развитие искусства, несущего огромную духовно-воспитательную силу. (26)Жизнь без смысла при таких условиях становится опаснее, чем когда бы то ни было. (27)Возможности созидания могут стать средствами всеобщего разрушения. (28)Ведь сами по себе они не хороши и не плохи, они лишь мощная, неопределённая «возможность», дремлющая огненная гора, непредсказуемая и своенравная во всём.(29)Современное человечество должно хотя бы интуитивно чувствовать, «куда» оно идёт, «зачем» ему даны эти возможности, «как» надо употребить, применить всё это, чтобы творческий путь познания не превратился в путь руин. (30)Что получится, если кучка лишённых духовных корней и нравственно разнузданных «завоевателей мира» начнёт возиться с инструментами современной химии, техники и науки?(31)Несчастье современного человека велико, ибо ему не хватает главного – смысла жизни. (32)Он должен отправиться на поиски. (33)И пока он не найдёт главного, беды и опасности будут подстерегать всё чаще и чаще. (34)Несмотря на всю мощь его разума и широту его возможностей. (По И.А. Ильину*)*Иван Александрович Ильин (1883–1954) – известный религиозный философ, писатель и публицист русского зарубежья.(13)Как богато человечество благами низшего порядка! (14) И будет делаться всё богаче. ",
        "attachments": [],
        "question": {
            "type": "matching",
            "left": [
                {
                    "id": "A",
                    "placeholder": "(А)________"
                },
                {
                    "id": "B",
                    "placeholder": "(Б)________"
                },
                {
                    "id": "C",
                    "placeholder": "(В)________"
                },
                {
                    "id": "D",
                    "placeholder": "(Г)________"
                }
            ],
            "choices": [
                {
                    "id": "1",
                    "text": "1 парцелляция"
                },
                {
                    "id": "2",
                    "text": "2 метафора(-"
                },
                {
                    "id": "3",
                    "text": "3"
                },
                {
                    "id": "4",
                    "text": "4 инверсия"
                },
                {
                    "id": "5",
                    "text": "5 лексический повтор"
                },
                {
                    "id": "6",
                    "text": "6 риторические вопросы"
                },
                {
                    "id": "7",
                    "text": "7 гипербола"
                },
                {
                    "id": "8",
                    "text": "8 сравнение(-"
                },
                {
                    "id": "9",
                    "text": "9"
                }
            ]
        },
        "solution": {
            "correct": {
                "A": "4",
                "B": "1",
                "C": "8",
                "D": "2"
            }
        },
        "score": 4
    },
    {
        "id": "27",
        "text": "Напишите сочинение по прочитанному тексту.Сформулируйте одну из проблем, поставленных автором текста.Прокомментируйте сформулированную проблему. Включите в комментарий два примера-иллюстрации из прочитанного текста, которые, по Вашему мнению, важны для понимания проблемы исходного текста (избегайте чрезмерного цитирования). Поясните значение каждого примера и укажите смысловую связь между ними.Сформулируйте позицию автора (рассказчика). Выразите своё отношение к позиции автора по проблеме исходного текста (согласие или несогласие) и обоснуйте его.Объём сочинения — не менее 150 слов.Работа, написанная без опоры на прочитанный текст (не по данному тексту), не оценивается. Если сочинение представляет собой пересказанный или полностью переписанный исходный текст без каких бы то ни было комментариев, то такая работа оценивается 0 баллов.Сочинение пишите аккуратно, разборчивым почерком.(1)Жил однажды чудак… (2)Он был очень богат и имел всё из вещей, что человек может себе только пожелать. (3)Дом его украшали мраморные лестницы, персидские ковры и золочёная мебель. (4)В саду, окружавшем этот роскошный дворец, благоухали цветы, били прохладные фонтаны, заморские птицы услаждали слух своим причудливым пением.(5)Однако, несмотря на внешнее благополучие, наш чудак чувствовал, что ему не хватает чего-то самого главного, чего он даже и назвать не мог. (6)Человек решительный и отважный, он так много мог, он почти всё смел, но он не знал такого, к чему можно стремиться, и жизнь казалась ему бессмысленной и мёртвой. (7)Ничто не радовало его, и богатство, всё более умножаясь, постепенно становилось для него горестным бременем.(8)Тогда он пошёл к одной старой женщине, которая пестовала свою древнюю мудрость в пещере дремлющей огненной горы. (9)Чудак рассказал ей о своей беде, и старуха ответила ему: (10)«Отправляйся в большой мир, чтобы найти пропавшее. (11) Твоё несчастье велико: тебе не хватает главного, и, пока ты его не найдёшь, жизнь для тебя будет бедой и пыткой».(12)Эта сказка всегда приходит мне на ум, когда я думаю о современном мире и его духовном кризисе. (13)Как богато человечество благами низшего порядка! (14) И будет делаться всё богаче. (15)Пространство будет побеждено, таинственные формы материи будут открыты, и ими овладеют. (16)Всё новые и новые инструменты, средства и возможности будут предоставлены человеку в распоряжение, но главное отсутствует.(17)«Как» земной жизни развивается безостановочно, но «зачем» – незаметно утрачивается. (18)Это так, как если бы человек, который страдает рассеянностью, играл в шахматы и выработал для себя дальновидный, сложный план, осуществление которого уже наполовину завершено, и вдруг он забывает свой план. (19)«Прекрасно! (20)Но для чего я всё это предпринимал? (21)Чего я, собственно, этим хотел?!» (22)Давайте вспомним о естественно-научных и технических изобретениях последнего столетия. (23)Электричество, динамит, культуры бактерий, железобетон, самолёт, радио, расщепление атома. (24)Само по себе этого довольно и сверхдостаточно, чтобы создать нечто великое. (25)Выход на такой заоблачный уровень, на такие пути предполагает наличие всеобъемлющего, окрылённого, дальновидного, целенаправленного сознания, развитие искусства, несущего огромную духовно-воспитательную силу. (26)Жизнь без смысла при таких условиях становится опаснее, чем когда бы то ни было. (27)Возможности созидания могут стать средствами всеобщего разрушения. (28)Ведь сами по себе они не хороши и не плохи, они лишь мощная, неопределённая «возможность», дремлющая огненная гора, непредсказуемая и своенравная во всём.(29)Современное человечество должно хотя бы интуитивно чувствовать, «куда» оно идёт, «зачем» ему даны эти возможности, «как» надо употребить, применить всё это, чтобы творческий путь познания не превратился в путь руин. (30)Что получится, если кучка лишённых духовных корней и нравственно разнузданных «завоевателей мира» начнёт возиться с инструментами современной химии, техники и науки?(31)Несчастье современного человека велико, ибо ему не хватает главного – смысла жизни. (32)Он должен отправиться на поиски. (33)И пока он не найдёт главного, беды и опасности будут подстерегать всё чаще и чаще. (34)Несмотря на всю мощь его разума и широту его возможностей. (По И.А. Ильину*)*Иван Александрович Ильин (1883–1954) – известный религиозный философ, писатель и публицист русского зарубежья.",
        "attachments": [],
        "question": {
            "type": "text",
            "min_length": 600,
            "max_length": 10000,
            "recommended_length": 1500
        },
        "solution": {
            "scoring": "manual"
        },
        "score": 24
    }
]